{
  "animations": [
    {
      "name": "default",
      "source_frames": [
        {
          "filename": "0.png",
          "hash": "3abfb932ef68ea75",
          "height": 88,
          "order": 0,
          "width": 174
        }
      ]
    }
  ],
  "asset_name": "building_2",
  "authored_scale_percentage": 100.0,
  "crop_canvas": {
    "shared_height": 88,
    "shared_width": 174
  },
  "digest": "4a32ce09f1343316",
  "generator_version": "image_cache_generator.v4",
  "schema_version": 2
}
