{
  "animations": [
    {
      "name": "default",
      "source_frames": [
        {
          "filename": "0.png",
          "hash": "4ec663f525749151",
          "height": 3139,
          "order": 0,
          "width": 3891
        }
      ]
    }
  ],
  "asset_name": "trail",
  "authored_scale_percentage": 215.99998474121094,
  "crop_canvas": {
    "shared_height": 3139,
    "shared_width": 3891
  },
  "digest": "0f42122cecd2a6b5",
  "generator_version": "image_cache_generator.v4",
  "schema_version": 2
}
